runpod_ariadne/__init__.py
runpod_ariadne/async_base_client.py
runpod_ariadne/base_model.py
runpod_ariadne/base_operation.py
runpod_ariadne/client.py
runpod_ariadne/custom_fields.py
runpod_ariadne/custom_mutations.py
runpod_ariadne/custom_queries.py
runpod_ariadne/custom_typing_fields.py
runpod_ariadne/enums.py
runpod_ariadne/exceptions.py
runpod_ariadne/input_types.py
runpod_ariadne/operations.py
runpod_ariadne-0.1.0.dist-info/METADATA
runpod_ariadne-0.1.0.dist-info/WHEEL
runpod_ariadne-0.1.0.dist-info/top_level.txt
runpod_ariadne-0.1.0.dist-info/RECORD
