Metadata-Version: 2.2
Name: runpod_ariadne
Version: 0.1.0
Summary: A third-party RunPod GraphQL client in Python generated using Ariadne.
Requires-Python: >=3.10
Provides-Extra: dev
Requires-Dist: ariadne-codegen[subscriptions]>=0.14.0; extra == "dev"
Requires-Dist: dotenv>=0.9.9; extra == "dev"
